app/__init__.py
app/main.py
app/models.py
lib/__init__.py
lib/operations.py
calculadora_fastapi_paulo_lopes-0.1.6.dist-info/METADATA
calculadora_fastapi_paulo_lopes-0.1.6.dist-info/WHEEL
calculadora_fastapi_paulo_lopes-0.1.6.dist-info/entry_points.txt
calculadora_fastapi_paulo_lopes-0.1.6.dist-info/top_level.txt
calculadora_fastapi_paulo_lopes-0.1.6.dist-info/RECORD
